odoo10_addon_stock_quant_merge-10.0.1.1.0-py3.8-nspkg.pth
odoo/addons/stock_quant_merge/README.rst
odoo/addons/stock_quant_merge/__init__.py
odoo/addons/stock_quant_merge/__manifest__.py
odoo/addons/stock_quant_merge/i18n/ca.po
odoo/addons/stock_quant_merge/i18n/cs_CZ.po
odoo/addons/stock_quant_merge/i18n/de.po
odoo/addons/stock_quant_merge/i18n/es.po
odoo/addons/stock_quant_merge/i18n/es_MX.po
odoo/addons/stock_quant_merge/i18n/fi.po
odoo/addons/stock_quant_merge/i18n/fr.po
odoo/addons/stock_quant_merge/i18n/gl.po
odoo/addons/stock_quant_merge/i18n/hr.po
odoo/addons/stock_quant_merge/i18n/it.po
odoo/addons/stock_quant_merge/i18n/nl.po
odoo/addons/stock_quant_merge/i18n/nl_NL.po
odoo/addons/stock_quant_merge/i18n/pt.po
odoo/addons/stock_quant_merge/i18n/pt_BR.po
odoo/addons/stock_quant_merge/i18n/ro.po
odoo/addons/stock_quant_merge/i18n/sl.po
odoo/addons/stock_quant_merge/i18n/stock_quant_merge.pot
odoo/addons/stock_quant_merge/i18n/tr.po
odoo/addons/stock_quant_merge/i18n/tr_TR.po
odoo/addons/stock_quant_merge/i18n/vi_VN.po
odoo/addons/stock_quant_merge/i18n/zh_CN.po
odoo/addons/stock_quant_merge/models/__init__.py
odoo/addons/stock_quant_merge/models/stock_move.py
odoo/addons/stock_quant_merge/models/stock_quant.py
odoo/addons/stock_quant_merge/static/description/icon.png
odoo/addons/stock_quant_merge/tests/__init__.py
odoo/addons/stock_quant_merge/tests/test_merge.py
odoo10_addon_stock_quant_merge-10.0.1.1.0.dist-info/METADATA
odoo10_addon_stock_quant_merge-10.0.1.1.0.dist-info/WHEEL
odoo10_addon_stock_quant_merge-10.0.1.1.0.dist-info/namespace_packages.txt
odoo10_addon_stock_quant_merge-10.0.1.1.0.dist-info/top_level.txt
odoo10_addon_stock_quant_merge-10.0.1.1.0.dist-info/RECORD
